deklare/__init__.py
deklare/core.py
deklare/deskribe.py
deklare/graph.py
deklare/persist.py
deklare/utils.py
deklare-0.1.3.dist-info/METADATA
deklare-0.1.3.dist-info/WHEEL
deklare-0.1.3.dist-info/licenses/LICENSE
deklare-0.1.3.dist-info/RECORD
