Metadata-Version: 2.4
Name: deklare
Version: 0.1.3
Summary: A data processing framework for data exploration
Author-email: Matthias Meyer <contact@niowniow.net>
License-File: LICENSE
Requires-Python: >=3.12.0
Requires-Dist: cachetools>=5.3.3
Requires-Dist: compress-pickle>=2.1.0
Requires-Dist: dask>=2024.5.1
Requires-Dist: pandas>=2.2.3
Requires-Dist: zarr>=2.18.2
